match_predicting_ann_server_pub_api/__init__.py
match_predicting_ann_server_pub_api/__main__.py
match_predicting_ann_server_pub_api/encoder.py
match_predicting_ann_server_pub_api/typing_utils.py
match_predicting_ann_server_pub_api/util.py
match_predicting_ann_server_pub_api/controllers/__init__.py
match_predicting_ann_server_pub_api/controllers/dummy_controller.py
match_predicting_ann_server_pub_api/controllers/network_controller.py
match_predicting_ann_server_pub_api/controllers/security_controller.py
match_predicting_ann_server_pub_api/models/__init__.py
match_predicting_ann_server_pub_api/models/base_model.py
match_predicting_ann_server_pub_api/models/dummy_dto.py
match_predicting_ann_server_pub_api/models/network_dto.py
match_predicting_ann_server_pub_api/models/predicting_data.py
match_predicting_ann_server_pub_api/models/training_data.py
match_predicting_ann_server_pub_api/models/training_match_dto.py
match_predicting_ann_server_pub_api/models/training_network_dto.py
match_predicting_ann_server_pub_api/models/training_progress_message.py
match_predicting_ann_server_pub_api/models/training_request_dto.py
match_predicting_ann_server_pub_api/openapi/openapi.yaml
match_predicting_ann_server_pub_api/test/__init__.py
match_predicting_ann_server_pub_api-7.13.dist-info/METADATA
match_predicting_ann_server_pub_api-7.13.dist-info/WHEEL
match_predicting_ann_server_pub_api-7.13.dist-info/entry_points.txt
match_predicting_ann_server_pub_api-7.13.dist-info/top_level.txt
match_predicting_ann_server_pub_api-7.13.dist-info/RECORD
