Metadata-Version: 2.4
Name: match_predicting_ann_server_pub_api
Version: 7.13
Summary: Match Predicting ANN Server Public API
Home-page: https://github.com/magistvan/match-predicting-ann-server-client
Author-email: magistvan@yahoo.com
Keywords: OpenAPI,Match Predicting ANN Server Public API
Requires-Dist: connexion>=2.0.2
Requires-Dist: swagger-ui-bundle>=0.0.2
Requires-Dist: python_dateutil>=2.6.0
Dynamic: author-email
Dynamic: description
Dynamic: home-page
Dynamic: keywords
Dynamic: requires-dist
Dynamic: summary
